<annotation>
	<folder>new</folder>
	<filename>img19.jpg</filename>
	<path>C:\Users\86151\Desktop\sample\new\img19.jpg</path>
	<source>
		<database>Unknown</database>
	</source>
	<size>
		<width>600</width>
		<height>600</height>
		<depth>1</depth>
	</size>
	<segmented>0</segmented>
	<object>
		<name>broken</name>
		<pose>Unspecified</pose>
		<truncated>0</truncated>
		<difficult>0</difficult>
		<bndbox>
			<xmin>337</xmin>
			<ymin>553</ymin>
			<xmax>386</xmax>
			<ymax>599</ymax>
		</bndbox>
	</object>
	<object>
		<name>broken</name>
		<pose>Unspecified</pose>
		<truncated>0</truncated>
		<difficult>0</difficult>
		<bndbox>
			<xmin>351</xmin>
			<ymin>489</ymin>
			<xmax>399</xmax>
			<ymax>553</ymax>
		</bndbox>
	</object>
	<object>
		<name>broken</name>
		<pose>Unspecified</pose>
		<truncated>0</truncated>
		<difficult>0</difficult>
		<bndbox>
			<xmin>370</xmin>
			<ymin>412</ymin>
			<xmax>408</xmax>
			<ymax>488</ymax>
		</bndbox>
	</object>
</annotation>
