<annotation>
	<folder>new</folder>
	<filename>img2818.jpg</filename>
	<path>C:\Users\86151\Desktop\sample\new\img2818.jpg</path>
	<source>
		<database>Unknown</database>
	</source>
	<size>
		<width>600</width>
		<height>600</height>
		<depth>1</depth>
	</size>
	<segmented>0</segmented>
	<object>
		<name>scratch</name>
		<pose>Unspecified</pose>
		<truncated>0</truncated>
		<difficult>0</difficult>
		<bndbox>
			<xmin>5</xmin>
			<ymin>341</ymin>
			<xmax>42</xmax>
			<ymax>380</ymax>
		</bndbox>
	</object>
	<object>
		<name>scratch</name>
		<pose>Unspecified</pose>
		<truncated>0</truncated>
		<difficult>0</difficult>
		<bndbox>
			<xmin>120</xmin>
			<ymin>171</ymin>
			<xmax>146</xmax>
			<ymax>220</ymax>
		</bndbox>
	</object>
</annotation>
