<annotation>
	<folder>new</folder>
	<filename>img5599.jpg</filename>
	<path>C:\Users\86151\Desktop\sample\new\img5599.jpg</path>
	<source>
		<database>Unknown</database>
	</source>
	<size>
		<width>600</width>
		<height>600</height>
		<depth>1</depth>
	</size>
	<segmented>0</segmented>
	<object>
		<name>broken</name>
		<pose>Unspecified</pose>
		<truncated>0</truncated>
		<difficult>0</difficult>
		<bndbox>
			<xmin>302</xmin>
			<ymin>336</ymin>
			<xmax>430</xmax>
			<ymax>432</ymax>
		</bndbox>
	</object>
	<object>
		<name>broken</name>
		<pose>Unspecified</pose>
		<truncated>0</truncated>
		<difficult>0</difficult>
		<bndbox>
			<xmin>299</xmin>
			<ymin>4</ymin>
			<xmax>447</xmax>
			<ymax>299</ymax>
		</bndbox>
	</object>
</annotation>
