<annotation>
	<folder>new</folder>
	<filename>img666.jpg</filename>
	<path>C:\Users\86151\Desktop\sample\new\img666.jpg</path>
	<source>
		<database>Unknown</database>
	</source>
	<size>
		<width>600</width>
		<height>600</height>
		<depth>1</depth>
	</size>
	<segmented>0</segmented>
	<object>
		<name>scratch</name>
		<pose>Unspecified</pose>
		<truncated>0</truncated>
		<difficult>0</difficult>
		<bndbox>
			<xmin>307</xmin>
			<ymin>80</ymin>
			<xmax>334</xmax>
			<ymax>99</ymax>
		</bndbox>
	</object>
	<object>
		<name>scratch</name>
		<pose>Unspecified</pose>
		<truncated>0</truncated>
		<difficult>0</difficult>
		<bndbox>
			<xmin>514</xmin>
			<ymin>327</ymin>
			<xmax>561</xmax>
			<ymax>358</ymax>
		</bndbox>
	</object>
	<object>
		<name>black_border</name>
		<pose>Unspecified</pose>
		<truncated>1</truncated>
		<difficult>0</difficult>
		<bndbox>
			<xmin>583</xmin>
			<ymin>30</ymin>
			<xmax>600</xmax>
			<ymax>174</ymax>
		</bndbox>
	</object>
</annotation>
